kedrogen/__init__.py
kedrogen/__main__.py
kedrogen/cli.py
kedrogen/main.py
kedrogen/utils.py
kedrogen-0.3.0.dist-info/LICENSE
kedrogen-0.3.0.dist-info/METADATA
kedrogen-0.3.0.dist-info/WHEEL
kedrogen-0.3.0.dist-info/entry_points.txt
kedrogen-0.3.0.dist-info/RECORD
